ghactions_publishing_test/__init__.py
ghactions_publishing_test/__version__.py
ghactions_publishing_test-0.1.11.dist-info/METADATA
ghactions_publishing_test-0.1.11.dist-info/WHEEL
ghactions_publishing_test-0.1.11.dist-info/top_level.txt
ghactions_publishing_test-0.1.11.dist-info/RECORD
